nautobot_device_onboarding/__init__.py
nautobot_device_onboarding/app-config-schema.json
nautobot_device_onboarding/choices.py
nautobot_device_onboarding/command_mappers/arista_eos.yml
nautobot_device_onboarding/command_mappers/aruba_aoscx.yml
nautobot_device_onboarding/command_mappers/aruba_os.yml
nautobot_device_onboarding/command_mappers/brocade_fastiron.yml
nautobot_device_onboarding/command_mappers/cisco_ios.yml
nautobot_device_onboarding/command_mappers/cisco_nxos.yml
nautobot_device_onboarding/command_mappers/cisco_wlc.yml
nautobot_device_onboarding/command_mappers/cisco_xe.yml
nautobot_device_onboarding/command_mappers/cisco_xr.yml
nautobot_device_onboarding/command_mappers/f5_tmsh.yml
nautobot_device_onboarding/command_mappers/hp_comware.yml
nautobot_device_onboarding/command_mappers/hp_procurve.yml
nautobot_device_onboarding/command_mappers/juniper_junos.yml
nautobot_device_onboarding/command_mappers/paloalto_panos.yml
nautobot_device_onboarding/constants.py
nautobot_device_onboarding/datasources.py
nautobot_device_onboarding/diffsync/__init__.py
nautobot_device_onboarding/diffsync/adapters/__init__.py
nautobot_device_onboarding/diffsync/adapters/sync_devices_adapters.py
nautobot_device_onboarding/diffsync/adapters/sync_network_data_adapters.py
nautobot_device_onboarding/diffsync/models/sync_devices_models.py
nautobot_device_onboarding/diffsync/models/sync_network_data_models.py
nautobot_device_onboarding/exceptions.py
nautobot_device_onboarding/jinja_filters.py
nautobot_device_onboarding/jobs.py
nautobot_device_onboarding/migrations/0001_initial.py
nautobot_device_onboarding/migrations/0001_squash__0001_0004_0005_0006.py
nautobot_device_onboarding/migrations/0002_create_onboardingdevice.py
nautobot_device_onboarding/migrations/0003_onboardingtask_label.py
nautobot_device_onboarding/migrations/0004_migrate_to_extras_role_part_1.py
nautobot_device_onboarding/migrations/0004_migrate_to_extras_role_part_2.py
nautobot_device_onboarding-5.2.1.dist-info/LICENSE
nautobot_device_onboarding-5.2.1.dist-info/METADATA
nautobot_device_onboarding-5.2.1.dist-info/WHEEL
nautobot_device_onboarding-5.2.1.dist-info/RECORD
