Metadata-Version: 2.3
Name: nautobot-device-onboarding
Version: 5.2.1
Summary: A app for Nautobot to easily onboard new devices.
License: Apache-2.0
Keywords: nautobot,nautobot-app,nautobot-plugin
Author: Network to Code, LLC
Author-email: info@networktocode.com
Requires-Python: >=3.10,<3.14
Classifier: Development Status :: 5 - Production/Stable
Classifier: Intended Audience :: Developers
Classifier: License :: OSI Approved :: Apache Software License
Classifier: Programming Language :: Python :: 3
Classifier: Programming Language :: Python :: 3.10
Classifier: Programming Language :: Python :: 3.11
Classifier: Programming Language :: Python :: 3.12
Classifier: Programming Language :: Python :: 3.13
Provides-Extra: all
Requires-Dist: jdiff (>=1.0.1,<2.0.0)
Requires-Dist: napalm (>=4.1.0,<6.0.0)
Requires-Dist: nautobot (>=3.0.0,<4.0.0)
Requires-Dist: nautobot-plugin-nornir (>=3.0.0,<4.0.0)
Requires-Dist: nautobot-ssot (>=4.0.0,<5.0.0)
Requires-Dist: netutils (>=1.9.1,<2.0.0)
Requires-Dist: ntc-templates (>=7.0.0,<8.0.0)
Requires-Dist: ttp (>=0.9.0,<0.10.0)
Requires-Dist: zipp (>=3.4.0,<4.0.0)
Project-URL: Homepage, https://github.com/nautobot/nautobot-app-device-onboarding
Project-URL: Repository, https://github.com/nautobot/nautobot-app-device-onboarding
